numerai/__init__.py
numerai/data.py
numerai/model_dispatcher.py
numerai/scoring.py
numerai/secrets.py
numerai/train.py
marloz_numerai-0.1.dist-info/LICENSE
marloz_numerai-0.1.dist-info/METADATA
marloz_numerai-0.1.dist-info/WHEEL
marloz_numerai-0.1.dist-info/top_level.txt
marloz_numerai-0.1.dist-info/RECORD
