Metadata-Version: 2.1
Name: marloz-numerai
Version: 0.1
Summary: Scripts used for https://numer.ai/ competition
Home-page: https://github.com/marloz/numerai
Author: Martynas Lozys
Author-email: martynaslozys@gmail.com
License: UNKNOWN
Platform: UNKNOWN
